napari_plugin_search/__init__.py
napari_plugin_search/_dock_widget.py
napari_plugin_search/_tests/__init__.py
napari_plugin_search/_tests/test_dock_widget.py
napari_plugin_search-0.1.4.dist-info/LICENSE
napari_plugin_search-0.1.4.dist-info/METADATA
napari_plugin_search-0.1.4.dist-info/WHEEL
napari_plugin_search-0.1.4.dist-info/entry_points.txt
napari_plugin_search-0.1.4.dist-info/top_level.txt
napari_plugin_search-0.1.4.dist-info/RECORD
