Metadata-Version: 2.1
Name: napari-plugin-search
Version: 0.1.4
Summary: Find napari plugins
Home-page: https://github.com/haesleinhuepf/napari-plugin-search
Author: Robert Haase
Author-email: robert.haase@tu-dresden.de
License: BSD-3-Clause
Project-URL: Bug Tracker, https://github.com/haesleinhuepf/napari-plugin-search/issues
Project-URL: Documentation, https://github.com/haesleinhuepf/napari-plugin-search#README.md
Project-URL: Source Code, https://github.com/haesleinhuepf/napari-plugin-search
Project-URL: User Support, https://github.com/haesleinhuepf/napari-plugin-search/issues
Classifier: Development Status :: 2 - Pre-Alpha
Classifier: Intended Audience :: Developers
Classifier: Framework :: napari
Classifier: Topic :: Scientific/Engineering :: Image Processing
Classifier: Programming Language :: Python
Classifier: Programming Language :: Python :: 3
Classifier: Programming Language :: Python :: 3.7
Classifier: Programming Language :: Python :: 3.8
Classifier: Programming Language :: Python :: 3.9
Classifier: Operating System :: OS Independent
Classifier: License :: OSI Approved :: BSD License
Requires-Python: >=3.7
License-File: LICENSE
Requires-Dist: napari-plugin-engine (>=0.1.4)
Requires-Dist: numpy
Requires-Dist: napari-tools-menu
